asap7_hdl21
