Metadata-Version: 2.1
Name: asap7-hdl21
Version: 4.0.0
Summary: ASAP7 PDK Package for Hdl21
Home-page: https://github.com/dan-fritchman/Hdl21
Author: Dan Fritchman
Requires-Python: >=3.7
Provides-Extra: dev
